LICENSE
MANIFEST.in
README.rst
requirements-build.txt
requirements-docs.txt
requirements-test.txt
requirements.txt
setup.cfg
setup.py
docs/devguide.rst
docs/index.rst
docs/migration.rst
docs/apidoc/index.rst
docs/apidoc/qtils.collections.rst
docs/apidoc/qtils.formatting.rst
docs/apidoc/qtils.log_utils.rst
docs/apidoc/qtils.properties.rst
docs/apidoc/qtils.string_utils.rst
docs/tutorial/collections.rst
docs/tutorial/formatting.rst
docs/tutorial/index.rst
docs/tutorial/log_utils.rst
docs/tutorial/properties.rst
docs/tutorial/string_utils.rst
src/qtils/__init__.py
src/qtils/collections.py
src/qtils/formatting.py
src/qtils/log_utils.py
src/qtils/properties.py
src/qtils/string_utils.py
src/qtils.egg-info/PKG-INFO
src/qtils.egg-info/SOURCES.txt
src/qtils.egg-info/dependency_links.txt
src/qtils.egg-info/not-zip-safe
src/qtils.egg-info/top_level.txt