Metadata-Version: 1.2
Name: qtils
Version: 0.10.0
Summary: Qtils - pronounces as `cuteels` - is a syntactic sugar library to make sweet Python coding even sweeter.
Home-page: https://github.com/ultralightweight/qtils
Author: Daniel Kovacs <@neonihil>
Author-email: mondomhogynincsen@gmail.com
Maintainer: Daniel Kovacs
Maintainer-email: mondomhogynincsen@gmail.com
License: License :: OSI Approved :: GNU Lesser General Public License v3 (LGPLv3)
Platform: UNKNOWN
Classifier: Development Status :: 5 - Production/Stable
Classifier: Intended Audience :: Developers
Classifier: License :: OSI Approved :: GNU Lesser General Public License v3 (LGPLv3)
Classifier: Operating System :: OS Independent
Classifier: Programming Language :: Python :: 3
Classifier: Topic :: Software Development :: Libraries
